rekha/__init__.py
rekha/_version.py
rekha/theme.py
rekha/plots/__init__.py
rekha/plots/bar.py
rekha/plots/base.py
rekha/plots/box.py
rekha/plots/cdf.py
rekha/plots/heatmap.py
rekha/plots/histogram.py
rekha/plots/line.py
rekha/plots/scatter.py
rekha/utils/__init__.py
rekha/utils/colors.py
rekha/utils/data.py
rekha/utils/layout.py
rekha-0.0.2.dist-info/licenses/LICENSE
rekha-0.0.2.dist-info/METADATA
rekha-0.0.2.dist-info/WHEEL
rekha-0.0.2.dist-info/top_level.txt
rekha-0.0.2.dist-info/RECORD
