Metadata-Version: 2.4
Name: rekha
Version: 0.0.2
Summary: Beautiful matplotlib visualizations with a Plotly Express-like interface
Author-email: Vajra Team <team@project-vajra.org>
Maintainer-email: Vajra Team <team@project-vajra.org>
License: Apache-2.0
Project-URL: Homepage, https://github.com/project-vajra/rekha
Project-URL: Documentation, https://project-vajra.github.io/rekha
Project-URL: Repository, https://github.com/project-vajra/rekha
Project-URL: Bug Tracker, https://github.com/project-vajra/rekha/issues
Project-URL: Changelog, https://github.com/project-vajra/rekha/blob/main/CHANGELOG.md
Keywords: matplotlib,plotting,visualization,data-science,plotly-express
Classifier: Development Status :: 4 - Beta
Classifier: Intended Audience :: Developers
Classifier: Intended Audience :: Science/Research
Classifier: License :: OSI Approved :: Apache Software License
Classifier: Operating System :: OS Independent
Classifier: Programming Language :: Python :: 3
Classifier: Programming Language :: Python :: 3.12
Classifier: Topic :: Scientific/Engineering :: Visualization
Classifier: Topic :: Software Development :: Libraries :: Python Modules
Requires-Python: >=3.12
License-File: LICENSE
Requires-Dist: matplotlib>=3.8.0
Requires-Dist: numpy>=1.21.0
Requires-Dist: pandas>=1.3.0
Requires-Dist: humanize>=4.0.0
Provides-Extra: dev
Requires-Dist: pytest>=6.0; extra == "dev"
Requires-Dist: pytest-cov; extra == "dev"
Requires-Dist: pytest-html; extra == "dev"
Requires-Dist: pytest-xdist; extra == "dev"
Requires-Dist: coverage[toml]; extra == "dev"
Requires-Dist: black; extra == "dev"
Requires-Dist: isort; extra == "dev"
Requires-Dist: autoflake; extra == "dev"
Requires-Dist: pyright; extra == "dev"
Requires-Dist: codespell; extra == "dev"
Requires-Dist: pre-commit; extra == "dev"
Provides-Extra: docs
Requires-Dist: sphinx>=4.0; extra == "docs"
Requires-Dist: furo>=2023.9.10; extra == "docs"
Requires-Dist: myst-parser>=0.18; extra == "docs"
Requires-Dist: sphinx-autobuild>=2021.3.14; extra == "docs"
Requires-Dist: sphinx-copybutton>=0.5.0; extra == "docs"
Requires-Dist: numpydoc>=1.4.0; extra == "docs"
Requires-Dist: nbsphinx>=0.8.0; extra == "docs"
Requires-Dist: jupyter>=1.0.0; extra == "docs"
Requires-Dist: linkify-it-py>=2.0.0; extra == "docs"
Provides-Extra: all
Requires-Dist: rekha[dev,docs,examples]; extra == "all"
Provides-Extra: examples
Requires-Dist: jupyter; extra == "examples"
Requires-Dist: scikit-learn; extra == "examples"
Requires-Dist: scipy; extra == "examples"
Dynamic: license-file
